pcr/__init__.py
pcr/default_config.py
pcr/dist
pcr/misc.py
pcr/model/__init__.py
pcr/model/Backbone.py
pcr/model/Decoder.py
pcr/model/dgcnn_group.py
pcr/model/ImplicitFunction.py
pcr/model/MLP.py
pcr/model/PCRNetwork.py
pcr/model/Transformer.py
pcr/utils/__init__.py
pcr/utils/Denormalize.py
pcr/utils/Normalize.py
hyperpcr-0.3.7.dist-info/WHEEL
hyperpcr-0.3.7.dist-info/METADATA
hyperpcr-0.3.7.dist-info/RECORD
