Metadata-Version: 2.1
Name: hyperpcr
Version: 0.3.7
Summary: Point Cloud Reconstruction with HyperNetwork
Author: andrearosasco
Author-email: andrea.rosasco@iit.it
Requires-Python: >=3.6,<4.0
Classifier: Programming Language :: Python :: 3
Classifier: Programming Language :: Python :: 3.10
Classifier: Programming Language :: Python :: 3.6
Classifier: Programming Language :: Python :: 3.7
Classifier: Programming Language :: Python :: 3.8
Classifier: Programming Language :: Python :: 3.9
Requires-Dist: requests (>=2.17,<3.0)
Requires-Dist: rich (>=12.2.0,<13.0.0)
Requires-Dist: timm (>=0.5.4,<0.6.0)
